setup.py
cw_sumtool/__init__.py
cw_sumtool/sum.py
cw_sumtool.egg-info/PKG-INFO
cw_sumtool.egg-info/SOURCES.txt
cw_sumtool.egg-info/dependency_links.txt
cw_sumtool.egg-info/top_level.txt