Metadata-Version: 1.0
Name: cw-sumtool
Version: 0.1.1
Summary: add tool
Home-page: UNKNOWN
Author: jack_chen
Author-email: 1390212397@qq.com
License: MIT Licence
Keywords: add
Platform: any
